[
    {
        "pset": [
            "<schema.org/isProprietary>",
            "<schema.org/manufacturer>",
            "<schema.org/name>",
            "<schema.org/targetPopulation>",
            "isa:<schema.org/DietarySupplement>"
        ],
        "count": 3154.0
    },
    {
        "pset": [
            "<schema.org/alternateName>",
            "<schema.org/description>",
            "<schema.org/name>",
            "isa:<schema.org/DietarySupplement>"
        ],
        "count": 611.0
    },
    {
        "pset": [
            "<schema.org/additionalType>",
            "<schema.org/alternateName>",
            "<schema.org/code>",
            "<schema.org/description>",
            "<schema.org/disambiguatingDescription>",
            "<schema.org/image>",
            "<schema.org/mainEntityOfPage>",
            "<schema.org/medicineSystem>",
            "<schema.org/name>",
            "<schema.org/recognizingAuthority>",
            "<schema.org/relevantSpecialty>",
            "<schema.org/sameAs>",
            "<schema.org/url>",
            "isa:<schema.org/DietarySupplement>"
        ],
        "count": 274.0
    },
    {
        "pset": [
            "<schema.org/description>",
            "<schema.org/image>",
            "<schema.org/name>",
            "<schema.org/sameAs>",
            "<schema.org/url>",
            "isa:<schema.org/DietarySupplement>"
        ],
        "count": 175.0
    },
    {
        "pset": [
            "<schema.org/activeIngredient>",
            "<schema.org/description>",
            "<schema.org/image>",
            "<schema.org/name>",
            "<schema.org/recommendedIntake>",
            "isa:<schema.org/DietarySupplement>"
        ],
        "count": 156.0
    },
    {
        "pset": [
            "<schema.org/isProprietary>",
            "<schema.org/manufacturer>",
            "<schema.org/name>",
            "<schema.org/proprietaryName>",
            "<schema.org/targetPopulation>",
            "isa:<schema.org/DietarySupplement>"
        ],
        "count": 129.0
    },
    {
        "pset": [
            "<schema.org/image>",
            "<schema.org/manufacturer>",
            "<schema.org/name>",
            "<schema.org/url>",
            "isa:<schema.org/DietarySupplement>"
        ],
        "count": 116.0
    },
    {
        "pset": [
            "<schema.org/activeIngredient>",
            "<schema.org/legalStatus>",
            "<schema.org/manufacturer>",
            "<schema.org/proprietaryName>",
            "<schema.org/targetPopulation>",
            "isa:<schema.org/DietarySupplement>"
        ],
        "count": 84.0
    },
    {
        "pset": [
            "<schema.org/background>",
            "<schema.org/description>",
            "<schema.org/name>",
            "<schema.org/nonProprietaryName>",
            "<schema.org/url>",
            "isa:<schema.org/DietarySupplement>"
        ],
        "count": 45.0
    },
    {
        "pset": [
            "<schema.org/alternateName>",
            "<schema.org/description>",
            "<schema.org/mechanismOfAction>",
            "<schema.org/name>",
            "isa:<schema.org/DietarySupplement>"
        ],
        "count": 31.0
    },
    {
        "pset": [
            "<schema.org/activeIngredient>",
            "<schema.org/manufacturer>",
            "<schema.org/maximumIntake>",
            "<schema.org/recommendedIntake>",
            "isa:<schema.org/DietarySupplement>"
        ],
        "count": 26.0
    },
    {
        "pset": [
            "<schema.org/activeIngredient>",
            "<schema.org/description>",
            "<schema.org/image>",
            "<schema.org/isProprietary>",
            "<schema.org/mechanismOfAction>",
            "<schema.org/name>",
            "<schema.org/safetyConsideration>",
            "isa:<schema.org/DietarySupplement>"
        ],
        "count": 20.0
    },
    {
        "pset": [
            "<schema.org/alternateName>",
            "<schema.org/description>",
            "<schema.org/image>",
            "<schema.org/mechanismOfAction>",
            "<schema.org/name>",
            "isa:<schema.org/DietarySupplement>"
        ],
        "count": 15.0
    },
    {
        "pset": [
            "<schema.org/alternateName>",
            "<schema.org/description>",
            "<schema.org/image>",
            "<schema.org/isProprietary>",
            "<schema.org/mechanismOfAction>",
            "<schema.org/name>",
            "<schema.org/safetyConsideration>",
            "isa:<schema.org/DietarySupplement>"
        ],
        "count": 14.0
    },
    {
        "pset": [
            "<schema.org/activeIngredient>",
            "<schema.org/description>",
            "<schema.org/isProprietary>",
            "<schema.org/legalStatus>",
            "<schema.org/manufacturer>",
            "<schema.org/nonProprietaryName>",
            "<schema.org/proprietaryName>",
            "isa:<schema.org/DietarySupplement>"
        ],
        "count": 9.0
    },
    {
        "pset": [
            "<schema.org/activeIngredient>",
            "<schema.org/legalStatus>",
            "<schema.org/manufacturer>",
            "<schema.org/proprietaryName>",
            "isa:<schema.org/DietarySupplement>"
        ],
        "count": 9.0
    },
    {
        "pset": [
            "<schema.org/legalStatus>",
            "<schema.org/manufacturer>",
            "<schema.org/proprietaryName>",
            "isa:<schema.org/DietarySupplement>"
        ],
        "count": 8.0
    },
    {
        "pset": [
            "<schema.org/name>",
            "isa:<schema.org/DietarySupplement>"
        ],
        "count": 5.0
    },
    {
        "pset": [
            "<schema.org/activeIngredient>",
            "<schema.org/description>",
            "<schema.org/isProprietary>",
            "<schema.org/legalStatus>",
            "<schema.org/manufacturer>",
            "<schema.org/nonProprietaryName>",
            "<schema.org/proprietaryName>",
            "<schema.org/recommendedIntake>",
            "isa:<schema.org/DietarySupplement>"
        ],
        "count": 5.0
    },
    {
        "pset": [
            "<schema.org/guideline>",
            "<schema.org/recommendedIntake>",
            "<schema.org/study>",
            "isa:<schema.org/DietarySupplement>"
        ],
        "count": 4.0
    },
    {
        "pset": [
            "<schema.org/guideline>",
            "<schema.org/isProprietary>",
            "<schema.org/mechanismOfAction>",
            "<schema.org/recommendedIntake>",
            "<schema.org/study>",
            "isa:<schema.org/DietarySupplement>"
        ],
        "count": 4.0
    },
    {
        "pset": [
            "<schema.org/activeIngredient>",
            "<schema.org/description>",
            "<schema.org/isProprietary>",
            "<schema.org/legalStatus>",
            "<schema.org/manufacturer>",
            "<schema.org/nonProprietaryName>",
            "<schema.org/proprietaryName>",
            "<schema.org/recommendedIntake>",
            "<schema.org/targetPopulation>",
            "isa:<schema.org/DietarySupplement>"
        ],
        "count": 4.0
    },
    {
        "pset": [
            "<schema.org/activeIngredient>",
            "<schema.org/description>",
            "<schema.org/name>",
            "<schema.org/url>",
            "isa:<schema.org/DietarySupplement>"
        ],
        "count": 3.0
    },
    {
        "pset": [
            "<schema.org/activeIngredient>",
            "<schema.org/recommendedIntake>",
            "<schema.org/safetyConsideration>",
            "<schema.org/targetPopulation>",
            "isa:<schema.org/DietarySupplement>"
        ],
        "count": 2.0
    },
    {
        "pset": [
            "<schema.org/description>",
            "<schema.org/name>",
            "<schema.org/url>",
            "isa:<schema.org/DietarySupplement>"
        ],
        "count": 2.0
    },
    {
        "pset": [
            "<schema.org/activeIngredient>",
            "<schema.org/alternateName>",
            "<schema.org/background>",
            "<schema.org/image>",
            "<schema.org/isProprietary>",
            "<schema.org/maximumIntake>",
            "<schema.org/mechanismOfAction>",
            "<schema.org/name>",
            "<schema.org/proprietaryName>",
            "<schema.org/recommendedIntake>",
            "<schema.org/targetPopulation>",
            "<schema.org/url>",
            "isa:<schema.org/DietarySupplement>"
        ],
        "count": 2.0
    },
    {
        "pset": [
            "<schema.org/manufacturer>",
            "<schema.org/proprietaryName>",
            "<schema.org/url>",
            "isa:<schema.org/DietarySupplement>"
        ],
        "count": 2.0
    },
    {
        "pset": [
            "<schema.org/activeIngredient>",
            "<schema.org/alternateName>",
            "<schema.org/description>",
            "<schema.org/image>",
            "<schema.org/isproprietary>",
            "<schema.org/mainEntityOfPage>",
            "<schema.org/manufacturer>",
            "<schema.org/maximumIntake>",
            "<schema.org/name>",
            "<schema.org/nonProprietaryName>",
            "<schema.org/recommendedIntake>",
            "<schema.org/url>",
            "isa:<schema.org/DietarySupplement>"
        ],
        "count": 1.0
    },
    {
        "pset": [
            "<schema.org/description>",
            "<schema.org/image>",
            "<schema.org/name>",
            "<schema.org/url>",
            "isa:<schema.org/DietarySupplement>"
        ],
        "count": 1.0
    },
    {
        "pset": [
            "<schema.org/about>",
            "<schema.org/articleBody>",
            "<schema.org/author>",
            "<schema.org/dateModified>",
            "<schema.org/datePublished>",
            "<schema.org/description>",
            "<schema.org/headline>",
            "<schema.org/image>",
            "<schema.org/inLanguage>",
            "<schema.org/isFamilyFriendly>",
            "<schema.org/mainEntityOfPage>",
            "<schema.org/name>",
            "<schema.org/publisher>",
            "<schema.org/url>",
            "<schema.org/video>",
            "isa:<schema.org/Article>",
            "isa:<schema.org/DietarySupplement>",
            "isa:<schema.org/HealthTopicContent>"
        ],
        "count": 1.0
    },
    {
        "pset": [
            "<schema.org/aggregateRating>",
            "<schema.org/brand>",
            "<schema.org/description>",
            "<schema.org/gtin14>",
            "<schema.org/image>",
            "<schema.org/mpn>",
            "<schema.org/name>",
            "<schema.org/offers>",
            "<schema.org/review>",
            "<schema.org/sku>",
            "<schema.org/url>",
            "isa:<schema.org/DietarySupplement>",
            "isa:<schema.org/Product>"
        ],
        "count": 1.0
    },
    {
        "pset": [
            "<schema.org/activeIngredient>",
            "<schema.org/name>",
            "isa:<schema.org/DietarySupplement>"
        ],
        "count": 1.0
    },
    {
        "pset": [
            "<schema.org/activeIngredient>",
            "<schema.org/description>",
            "<schema.org/isProprietary>",
            "<schema.org/nonProprietaryName>",
            "isa:<schema.org/DietarySupplement>"
        ],
        "count": 1.0
    },
    {
        "pset": [
            "<schema.org/activeIngredient>",
            "<schema.org/guideline>",
            "<schema.org/isProprietary>",
            "<schema.org/mechanismOfAction>",
            "<schema.org/recommendedIntake>",
            "<schema.org/study>",
            "isa:<schema.org/DietarySupplement>"
        ],
        "count": 1.0
    },
    {
        "pset": [
            "<schema.org/activeIngredient>",
            "<schema.org/description>",
            "<schema.org/image>",
            "<schema.org/manufacturer>",
            "<schema.org/name>",
            "<schema.org/recommendedIntake>",
            "<schema.org/url>",
            "isa:<schema.org/DietarySupplement>"
        ],
        "count": 1.0
    },
    {
        "pset": [
            "<schema.org/aggregateRating>",
            "<schema.org/brand>",
            "<schema.org/description>",
            "<schema.org/gtin14>",
            "<schema.org/image>",
            "<schema.org/mpn>",
            "<schema.org/name>",
            "<schema.org/offers>",
            "<schema.org/review>",
            "<schema.org/sku>",
            "isa:<schema.org/DietarySupplement>",
            "isa:<schema.org/Product>"
        ],
        "count": 1.0
    },
    {
        "pset": [
            "<schema.org/aggregateRating>",
            "<schema.org/brand>",
            "<schema.org/description>",
            "<schema.org/image>",
            "<schema.org/name>",
            "<schema.org/offers>",
            "<schema.org/review>",
            "<schema.org/sku>",
            "isa:<schema.org/DietarySupplement>",
            "isa:<schema.org/Product>"
        ],
        "count": 1.0
    },
    {
        "pset": [
            "<schema.org/legalStatus>",
            "<schema.org/manufacturer>",
            "<schema.org/proprietaryName>",
            "<schema.org/targetPopulation>",
            "isa:<schema.org/DietarySupplement>"
        ],
        "count": 1.0
    },
    {
        "pset": [
            "<schema.org/activeIngredient>",
            "<schema.org/articleSection>",
            "<schema.org/author>",
            "<schema.org/commentCount>",
            "<schema.org/dateModified>",
            "<schema.org/datePublished>",
            "<schema.org/headline>",
            "<schema.org/image>",
            "<schema.org/inLanguage>",
            "<schema.org/isPartOf>",
            "<schema.org/keywords>",
            "<schema.org/mainEntityOfPage>",
            "<schema.org/potentialAction>",
            "<schema.org/publisher>",
            "<schema.org/thumbnailUrl>",
            "<schema.org/wordCount>",
            "isa:<schema.org/Article>",
            "isa:<schema.org/DietarySupplement>"
        ],
        "count": 1.0
    }
]