[
    {
        "pset": [
            "<schema.org/address>",
            "<schema.org/geo>",
            "<schema.org/image>",
            "<schema.org/name>",
            "<schema.org/openingHoursSpecification>",
            "<schema.org/sameAs>",
            "<schema.org/telephone>",
            "<schema.org/url>",
            "isa:<schema.org/InternetCafe>",
            "isa:<schema.org/WebPage>"
        ],
        "count": 723.0
    },
    {
        "pset": [
            "<schema.org/address>",
            "<schema.org/geo>",
            "<schema.org/image>",
            "<schema.org/name>",
            "<schema.org/openingHoursSpecification>",
            "<schema.org/sameAs>",
            "<schema.org/telephone>",
            "<schema.org/url>",
            "isa:<schema.org/InternetCafe>"
        ],
        "count": 226.0
    },
    {
        "pset": [
            "<schema.org/address>",
            "<schema.org/contactPoint>",
            "<schema.org/email>",
            "<schema.org/geo>",
            "<schema.org/image>",
            "<schema.org/logo>",
            "<schema.org/name>",
            "<schema.org/openingHours>",
            "<schema.org/priceRange>",
            "<schema.org/sameAs>",
            "<schema.org/telePhone>",
            "<schema.org/url>",
            "isa:<schema.org/InternetCafe>"
        ],
        "count": 171.0
    },
    {
        "pset": [
            "<schema.org/address>",
            "<schema.org/geo>",
            "<schema.org/image>",
            "<schema.org/name>",
            "<schema.org/telephone>",
            "<schema.org/url>",
            "isa:<schema.org/InternetCafe>"
        ],
        "count": 24.0
    },
    {
        "pset": [
            "<schema.org/address>",
            "<schema.org/contactPoint>",
            "<schema.org/description>",
            "<schema.org/geo>",
            "<schema.org/hasMap>",
            "<schema.org/image>",
            "<schema.org/logo>",
            "<schema.org/name>",
            "<schema.org/openingHoursSpecification>",
            "<schema.org/priceRange>",
            "<schema.org/telephone>",
            "<schema.org/url>",
            "isa:<schema.org/InternetCafe>"
        ],
        "count": 21.0
    },
    {
        "pset": [
            "<schema.org/address>",
            "<schema.org/aggregateRating>",
            "<schema.org/email>",
            "<schema.org/image>",
            "<schema.org/name>",
            "<schema.org/openingHours>",
            "<schema.org/paymentAccepted>",
            "<schema.org/priceRange>",
            "<schema.org/telephone>",
            "<schema.org/url>",
            "isa:<schema.org/InternetCafe>"
        ],
        "count": 19.0
    },
    {
        "pset": [
            "<schema.org/address>",
            "<schema.org/image>",
            "<schema.org/name>",
            "<schema.org/openingHoursSpecification>",
            "<schema.org/telephone>",
            "<schema.org/url>",
            "isa:<schema.org/InternetCafe>"
        ],
        "count": 18.0
    },
    {
        "pset": [
            "<schema.org/address>",
            "<schema.org/email>",
            "<schema.org/faxNumber>",
            "<schema.org/image>",
            "<schema.org/logo>",
            "<schema.org/name>",
            "<schema.org/telephone>",
            "<schema.org/url>",
            "isa:<schema.org/InternetCafe>"
        ],
        "count": 15.0
    },
    {
        "pset": [
            "<schema.org/address>",
            "<schema.org/email>",
            "<schema.org/geo>",
            "<schema.org/image>",
            "<schema.org/name>",
            "<schema.org/openingHours>",
            "<schema.org/openingHoursSpecification>",
            "<schema.org/paymentAccepted>",
            "<schema.org/priceRange>",
            "<schema.org/telePhone>",
            "<schema.org/url>",
            "isa:<schema.org/InternetCafe>"
        ],
        "count": 10.0
    },
    {
        "pset": [
            "<schema.org/address>",
            "<schema.org/description>",
            "<schema.org/name>",
            "isa:<schema.org/InternetCafe>"
        ],
        "count": 9.0
    },
    {
        "pset": [
            "<schema.org/additionalType>",
            "<schema.org/hasMap>",
            "<schema.org/logo>",
            "<schema.org/name>",
            "<schema.org/sameAs>",
            "<schema.org/url>",
            "isa:<schema.org/InternetCafe>"
        ],
        "count": 8.0
    },
    {
        "pset": [
            "<schema.org/address>",
            "<schema.org/geo>",
            "<schema.org/image>",
            "<schema.org/map>",
            "<schema.org/name>",
            "<schema.org/priceRange>",
            "<schema.org/servesCuisine>",
            "<schema.org/telephone>",
            "isa:<schema.org/InternetCafe>"
        ],
        "count": 7.0
    },
    {
        "pset": [
            "<schema.org/address>",
            "<schema.org/contactPoint>",
            "<schema.org/description>",
            "<schema.org/email>",
            "<schema.org/geo>",
            "<schema.org/hasMap>",
            "<schema.org/image>",
            "<schema.org/logo>",
            "<schema.org/name>",
            "<schema.org/openingHours>",
            "<schema.org/priceRange>",
            "<schema.org/telephone>",
            "<schema.org/url>",
            "isa:<schema.org/InternetCafe>"
        ],
        "count": 6.0
    },
    {
        "pset": [
            "<schema.org/address>",
            "<schema.org/image>",
            "<schema.org/name>",
            "<schema.org/openingHoursSpecification>",
            "<schema.org/priceRange>",
            "<schema.org/telephone>",
            "<schema.org/url>",
            "isa:<schema.org/InternetCafe>"
        ],
        "count": 3.0
    },
    {
        "pset": [
            "<schema.org/address>",
            "<schema.org/geo>",
            "<schema.org/image>",
            "<schema.org/name>",
            "<schema.org/openingHoursSpecification>",
            "<schema.org/priceRange>",
            "<schema.org/sameAs>",
            "<schema.org/telephone>",
            "<schema.org/url>",
            "isa:<schema.org/InternetCafe>"
        ],
        "count": 3.0
    },
    {
        "pset": [
            "<schema.org/image>",
            "<schema.org/name>",
            "<schema.org/sameAs>",
            "<schema.org/url>",
            "isa:<schema.org/InternetCafe>"
        ],
        "count": 2.0
    },
    {
        "pset": [
            "<schema.org/address>",
            "<schema.org/contactPoint>",
            "<schema.org/description>",
            "<schema.org/geo>",
            "<schema.org/image>",
            "<schema.org/name>",
            "<schema.org/priceRange>",
            "<schema.org/telephone>",
            "<schema.org/url>",
            "isa:<schema.org/InternetCafe>"
        ],
        "count": 2.0
    },
    {
        "pset": [
            "<schema.org/image>",
            "<schema.org/logo>",
            "<schema.org/name>",
            "<schema.org/openingHours>",
            "<schema.org/url>",
            "isa:<schema.org/InternetCafe>",
            "isa:<schema.org/Organization>"
        ],
        "count": 1.0
    },
    {
        "pset": [
            "<schema.org/image>",
            "<schema.org/name>",
            "<schema.org/openingHoursSpecification>",
            "isa:<schema.org/InternetCafe>"
        ],
        "count": 1.0
    },
    {
        "pset": [
            "<schema.org/address>",
            "<schema.org/geo>",
            "<schema.org/image>",
            "<schema.org/name>",
            "<schema.org/openingHoursSpecification>",
            "<schema.org/telephone>",
            "<schema.org/url>",
            "isa:<schema.org/InternetCafe>"
        ],
        "count": 1.0
    },
    {
        "pset": [
            "<schema.org/address>",
            "<schema.org/image>",
            "<schema.org/name>",
            "<schema.org/openingHoursSpecification>",
            "<schema.org/priceRange>",
            "<schema.org/sameAs>",
            "<schema.org/telephone>",
            "<schema.org/url>",
            "isa:<schema.org/InternetCafe>"
        ],
        "count": 1.0
    },
    {
        "pset": [
            "<schema.org/image>",
            "<schema.org/logo>",
            "<schema.org/name>",
            "<schema.org/openingHours>",
            "<schema.org/url>",
            "isa:<schema.org/InternetCafe>"
        ],
        "count": 1.0
    },
    {
        "pset": [
            "<schema.org/address>",
            "<schema.org/alternateName>",
            "<schema.org/areaServed>",
            "<schema.org/brand>",
            "<schema.org/currenciesAccepted>",
            "<schema.org/email>",
            "<schema.org/geo>",
            "<schema.org/hasMap>",
            "<schema.org/image>",
            "<schema.org/legalName>",
            "<schema.org/location>",
            "<schema.org/name>",
            "<schema.org/openingHoursSpecification>",
            "<schema.org/priceRange>",
            "<schema.org/sameAs>",
            "<schema.org/slogan>",
            "<schema.org/telephone>",
            "<schema.org/url>",
            "isa:<schema.org/ComputerStore>",
            "isa:<schema.org/ElectronicsStore>",
            "isa:<schema.org/InternetCafe>"
        ],
        "count": 1.0
    },
    {
        "pset": [
            "<schema.org/address>",
            "<schema.org/currenciesAccepted>",
            "<schema.org/email>",
            "<schema.org/image>",
            "<schema.org/location>",
            "<schema.org/logo>",
            "<schema.org/name>",
            "<schema.org/paymentAccepted>",
            "<schema.org/priceRange>",
            "<schema.org/sameAs>",
            "<schema.org/telephone>",
            "<schema.org/url>",
            "isa:<schema.org/InternetCafe>",
            "isa:<schema.org/Organization>",
            "isa:<schema.org/Place>"
        ],
        "count": 1.0
    },
    {
        "pset": [
            "<schema.org/address>",
            "<schema.org/faxNumber>",
            "<schema.org/geo>",
            "<schema.org/map>",
            "<schema.org/name>",
            "<schema.org/priceRange>",
            "<schema.org/servesCuisine>",
            "<schema.org/telephone>",
            "isa:<schema.org/InternetCafe>"
        ],
        "count": 1.0
    },
    {
        "pset": [
            "<schema.org/email>",
            "<schema.org/image>",
            "<schema.org/name>",
            "<schema.org/url>",
            "isa:<schema.org/InternetCafe>"
        ],
        "count": 1.0
    },
    {
        "pset": [
            "<schema.org/address>",
            "<schema.org/geo>",
            "<schema.org/image>",
            "<schema.org/name>",
            "<schema.org/openingHoursSpecification>",
            "<schema.org/priceRange>",
            "<schema.org/telephone>",
            "<schema.org/url>",
            "isa:<schema.org/InternetCafe>"
        ],
        "count": 1.0
    },
    {
        "pset": [
            "<schema.org/email>",
            "<schema.org/name>",
            "<schema.org/url>",
            "isa:<schema.org/InternetCafe>",
            "isa:<schema.org/Organization>"
        ],
        "count": 1.0
    },
    {
        "pset": [
            "<schema.org/address>",
            "<schema.org/contactPoint>",
            "<schema.org/description>",
            "<schema.org/name>",
            "<schema.org/openingHours>",
            "<schema.org/url>",
            "isa:<schema.org/InternetCafe>"
        ],
        "count": 1.0
    },
    {
        "pset": [
            "<schema.org/image>",
            "<schema.org/name>",
            "isa:<schema.org/InternetCafe>"
        ],
        "count": 1.0
    },
    {
        "pset": [
            "<schema.org/address>",
            "<schema.org/description>",
            "<schema.org/geo>",
            "<schema.org/hasMap>",
            "<schema.org/image>",
            "<schema.org/logo>",
            "<schema.org/mainEntityOfPage>",
            "<schema.org/map>",
            "<schema.org/name>",
            "<schema.org/openingHours>",
            "<schema.org/telephone>",
            "<schema.org/url>",
            "isa:<schema.org/InternetCafe>"
        ],
        "count": 1.0
    },
    {
        "pset": [
            "<schema.org/additionalType>",
            "<schema.org/hasMap>",
            "<schema.org/logo>",
            "<schema.org/name>",
            "<schema.org/openingHours>",
            "<schema.org/sameAs>",
            "<schema.org/telephone>",
            "<schema.org/url>",
            "isa:<schema.org/InternetCafe>"
        ],
        "count": 1.0
    },
    {
        "pset": [
            "<schema.org/name>",
            "<schema.org/openingHours>",
            "<schema.org/url>",
            "isa:<schema.org/InternetCafe>",
            "isa:<schema.org/Organization>"
        ],
        "count": 1.0
    },
    {
        "pset": [
            "<schema.org/address>",
            "<schema.org/aggregateRating>",
            "<schema.org/image>",
            "<schema.org/name>",
            "<schema.org/openingHoursSpecification>",
            "<schema.org/priceRange>",
            "<schema.org/telephone>",
            "<schema.org/url>",
            "isa:<schema.org/InternetCafe>"
        ],
        "count": 1.0
    },
    {
        "pset": [
            "<schema.org/address>",
            "<schema.org/email>",
            "<schema.org/image>",
            "<schema.org/logo>",
            "<schema.org/name>",
            "<schema.org/openingHoursSpecification>",
            "<schema.org/sameAs>",
            "<schema.org/telephone>",
            "<schema.org/url>",
            "isa:<schema.org/InternetCafe>",
            "isa:<schema.org/Organization>",
            "isa:<schema.org/Person>",
            "isa:<schema.org/Place>"
        ],
        "count": 1.0
    }
]