[
    {
        "pset": [
            "<schema.org/providesService>",
            "<schema.org/serviceUrl>",
            "isa:<schema.org/ServiceChannel>"
        ],
        "count": 198349.0
    },
    {
        "pset": [
            "<schema.org/serviceUrl>",
            "isa:<schema.org/ServiceChannel>"
        ],
        "count": 57821.0
    },
    {
        "pset": [
            "<schema.org/ServiceUrl>",
            "<schema.org/availableLanguage>",
            "isa:<schema.org/ServiceChannel>"
        ],
        "count": 33264.0
    },
    {
        "pset": [
            "<schema.org/servicePhone>",
            "isa:<schema.org/ServiceChannel>"
        ],
        "count": 10526.0
    },
    {
        "pset": [
            "<schema.org/availableLanguage>",
            "<schema.org/name>",
            "isa:<schema.org/ServiceChannel>"
        ],
        "count": 4993.0
    },
    {
        "pset": [
            "<schema.org/serviceLocation>",
            "<schema.org/serviceUrl>",
            "isa:<schema.org/ServiceChannel>"
        ],
        "count": 3122.0
    },
    {
        "pset": [
            "<schema.org/description>",
            "<schema.org/name>",
            "<schema.org/serviceUrl>",
            "isa:<schema.org/ServiceChannel>"
        ],
        "count": 1607.0
    },
    {
        "pset": [
            "<schema.org/name>",
            "<schema.org/servicePostalAddress>",
            "isa:<schema.org/ServiceChannel>"
        ],
        "count": 1386.0
    },
    {
        "pset": [
            "<schema.org/description>",
            "<schema.org/image>",
            "<schema.org/servicePhone>",
            "<schema.org/serviceUrl>",
            "isa:<schema.org/ServiceChannel>"
        ],
        "count": 1255.0
    },
    {
        "pset": [
            "<schema.org/availableLanguage>",
            "isa:<schema.org/ServiceChannel>"
        ],
        "count": 1165.0
    },
    {
        "pset": [
            "<schema.org/description>",
            "<schema.org/image>",
            "<schema.org/serviceUrl>",
            "isa:<schema.org/ServiceChannel>"
        ],
        "count": 1125.0
    },
    {
        "pset": [
            "<schema.org/availableLanguage>",
            "<schema.org/name>",
            "<schema.org/providesService>",
            "<schema.org/servicePhone>",
            "<schema.org/serviceURL>",
            "isa:<schema.org/ServiceChannel>"
        ],
        "count": 735.0
    },
    {
        "pset": [
            "<schema.org/description>",
            "<schema.org/serviceMobileApp>",
            "isa:<schema.org/ServiceChannel>"
        ],
        "count": 672.0
    },
    {
        "pset": [
            "<schema.org/name>",
            "isa:<schema.org/ServiceChannel>"
        ],
        "count": 569.0
    },
    {
        "pset": [
            "<schema.org/description>",
            "<schema.org/name>",
            "<schema.org/serviceLocation>",
            "<schema.org/servicePhone>",
            "<schema.org/serviceUrl>",
            "isa:<schema.org/ServiceChannel>"
        ],
        "count": 358.0
    },
    {
        "pset": [
            "<schema.org/availableLanguage>",
            "<schema.org/sameAs>",
            "<schema.org/servicePhone>",
            "<schema.org/serviceURL>",
            "isa:<schema.org/ServiceChannel>"
        ],
        "count": 327.0
    },
    {
        "pset": [
            "<schema.org/areaServed>",
            "<schema.org/audience>",
            "<schema.org/name>",
            "<schema.org/servicePhone>",
            "isa:<schema.org/ServiceChannel>"
        ],
        "count": 308.0
    },
    {
        "pset": [
            "<schema.org/serviceLocation>",
            "<schema.org/servicePhone>",
            "<schema.org/serviceUrl>",
            "isa:<schema.org/ServiceChannel>"
        ],
        "count": 298.0
    },
    {
        "pset": [
            "<schema.org/audience>",
            "<schema.org/offers>",
            "<schema.org/provider>",
            "isa:<schema.org/ServiceChannel>"
        ],
        "count": 213.0
    },
    {
        "pset": [
            "<schema.org/description>",
            "<schema.org/name>",
            "isa:<schema.org/ServiceChannel>"
        ],
        "count": 206.0
    },
    {
        "pset": [
            "<schema.org/availableLanguage>",
            "<schema.org/name>",
            "<schema.org/serviceLocation>",
            "isa:<schema.org/ServiceChannel>"
        ],
        "count": 186.0
    },
    {
        "pset": [
            "<schema.org/description>",
            "<schema.org/name>",
            "<schema.org/providesService>",
            "<schema.org/serviceUrl>",
            "isa:<schema.org/ServiceChannel>"
        ],
        "count": 183.0
    },
    {
        "pset": [
            "<schema.org/servicePhone>",
            "<schema.org/serviceURL>",
            "isa:<schema.org/ServiceChannel>"
        ],
        "count": 163.0
    },
    {
        "pset": [
            "<schema.org/servicePhone>",
            "<schema.org/serviceUrl>",
            "isa:<schema.org/ServiceChannel>"
        ],
        "count": 156.0
    },
    {
        "pset": [
            "<schema.org/areaServed>",
            "<schema.org/hoursAvailable>",
            "<schema.org/name>",
            "isa:<schema.org/ServiceChannel>"
        ],
        "count": 154.0
    },
    {
        "pset": [
            "<schema.org/areaServed>",
            "<schema.org/name>",
            "<schema.org/servicePhone>",
            "isa:<schema.org/ServiceChannel>"
        ],
        "count": 154.0
    },
    {
        "pset": [
            "<schema.org/ServiceLocation>",
            "<schema.org/image>",
            "<schema.org/processingTime>",
            "<schema.org/serviceUrl>",
            "isa:<schema.org/ServiceChannel>"
        ],
        "count": 154.0
    },
    {
        "pset": [
            "<schema.org/availableLanguage>",
            "<schema.org/providesService>",
            "<schema.org/servicePostalAddress>",
            "<schema.org/serviceURL>",
            "isa:<schema.org/ServiceChannel>"
        ],
        "count": 126.0
    },
    {
        "pset": [
            "<schema.org/address>",
            "<schema.org/areaServed>",
            "<schema.org/audience>",
            "<schema.org/availableChannel>",
            "<schema.org/description>",
            "<schema.org/geo>",
            "<schema.org/image>",
            "<schema.org/name>",
            "<schema.org/openingHoursSpecification>",
            "<schema.org/priceRange>",
            "<schema.org/provider>",
            "<schema.org/serviceLocation>",
            "<schema.org/servicePhone>",
            "<schema.org/serviceType>",
            "<schema.org/serviceUrl>",
            "<schema.org/telephone>",
            "<schema.org/url>",
            "isa:<schema.org/LocalBusiness>",
            "isa:<schema.org/Service>",
            "isa:<schema.org/ServiceChannel>"
        ],
        "count": 122.0
    },
    {
        "pset": [
            "<schema.org/availableLanguage>",
            "<schema.org/serviceUrl>",
            "isa:<schema.org/ServiceChannel>"
        ],
        "count": 109.0
    },
    {
        "pset": [
            "<schema.org/description>",
            "<schema.org/name>",
            "<schema.org/serviceLocation>",
            "<schema.org/serviceUrl>",
            "isa:<schema.org/ServiceChannel>"
        ],
        "count": 90.0
    },
    {
        "pset": [
            "<schema.org/serviceLocation>",
            "isa:<schema.org/ServiceChannel>"
        ],
        "count": 88.0
    },
    {
        "pset": [
            "<schema.org/description>",
            "<schema.org/name>",
            "<schema.org/servicePhone>",
            "<schema.org/serviceUrl>",
            "isa:<schema.org/ServiceChannel>"
        ],
        "count": 65.0
    },
    {
        "pset": [
            "<schema.org/name>",
            "<schema.org/serviceUrl>",
            "isa:<schema.org/ServiceChannel>"
        ],
        "count": 60.0
    },
    {
        "pset": [
            "<schema.org/name>",
            "<schema.org/serviceLocation>",
            "isa:<schema.org/ServiceChannel>"
        ],
        "count": 59.0
    },
    {
        "pset": [
            "<schema.org/serviceUrl>",
            "<schema.org/servicephone>",
            "isa:<schema.org/ServiceChannel>"
        ],
        "count": 54.0
    },
    {
        "pset": [
            "<schema.org/availableLanguage>",
            "<schema.org/name>",
            "<schema.org/serviceUrl>",
            "isa:<schema.org/ServiceChannel>"
        ],
        "count": 40.0
    },
    {
        "pset": [
            "<schema.org/name>",
            "<schema.org/servicePhone>",
            "<schema.org/serviceUrl>",
            "isa:<schema.org/ServiceChannel>"
        ],
        "count": 37.0
    },
    {
        "pset": [
            "<schema.org/name>",
            "<schema.org/serviceLocation>",
            "<schema.org/servicePhone>",
            "isa:<schema.org/ServiceChannel>"
        ],
        "count": 27.0
    },
    {
        "pset": [
            "<schema.org/contactPoint>",
            "<schema.org/description>",
            "<schema.org/image>",
            "<schema.org/name>",
            "<schema.org/serviceLocation>",
            "<schema.org/serviceUrl>",
            "isa:<schema.org/ServiceChannel>"
        ],
        "count": 27.0
    },
    {
        "pset": [
            "<schema.org/availableLanguage>",
            "<schema.org/serviceLocation>",
            "isa:<schema.org/ServiceChannel>"
        ],
        "count": 26.0
    },
    {
        "pset": [
            "<schema.org/audience>",
            "<schema.org/offers>",
            "<schema.org/provider>",
            "<schema.org/servicePhone>",
            "isa:<schema.org/ServiceChannel>"
        ],
        "count": 25.0
    },
    {
        "pset": [
            "<schema.org/areaServed>",
            "<schema.org/audience>",
            "<schema.org/availableChannel>",
            "<schema.org/description>",
            "<schema.org/image>",
            "<schema.org/name>",
            "<schema.org/provider>",
            "<schema.org/serviceLocation>",
            "<schema.org/servicePhone>",
            "<schema.org/serviceType>",
            "<schema.org/serviceUrl>",
            "<schema.org/url>",
            "isa:<schema.org/Service>",
            "isa:<schema.org/ServiceChannel>"
        ],
        "count": 25.0
    },
    {
        "pset": [
            "<schema.org/availableLanguage>",
            "<schema.org/processingTime>",
            "<schema.org/serviceLocation>",
            "<schema.org/servicePhone>",
            "<schema.org/serviceUrl>",
            "isa:<schema.org/ServiceChannel>"
        ],
        "count": 24.0
    },
    {
        "pset": [
            "<schema.org/name>",
            "<schema.org/url>",
            "isa:<schema.org/ServiceChannel>"
        ],
        "count": 24.0
    },
    {
        "pset": [
            "<schema.org/description>",
            "<schema.org/servicePhone>",
            "<schema.org/servicePostalAddress>",
            "<schema.org/serviceUrl>",
            "isa:<schema.org/ServiceChannel>"
        ],
        "count": 23.0
    },
    {
        "pset": [
            "<schema.org/potentialAction>",
            "<schema.org/serviceUrl>",
            "isa:<schema.org/ServiceChannel>"
        ],
        "count": 23.0
    },
    {
        "pset": [
            "<schema.org/description>",
            "<schema.org/name>",
            "<schema.org/providesService>",
            "<schema.org/serviceLocation>",
            "<schema.org/servicePostalAddress>",
            "isa:<schema.org/ServiceChannel>"
        ],
        "count": 23.0
    },
    {
        "pset": [
            "<schema.org/areaServed>",
            "<schema.org/availableChannel>",
            "<schema.org/description>",
            "<schema.org/provider>",
            "<schema.org/servicePhone>",
            "<schema.org/serviceType>",
            "<schema.org/serviceUrl>",
            "<schema.org/url>",
            "isa:<schema.org/Service>",
            "isa:<schema.org/ServiceChannel>"
        ],
        "count": 14.0
    },
    {
        "pset": [
            "<schema.org/availableLanguage>",
            "<schema.org/description>",
            "<schema.org/name>",
            "<schema.org/servicePhone>",
            "<schema.org/serviceUrl>",
            "isa:<schema.org/ServiceChannel>"
        ],
        "count": 13.0
    },
    {
        "pset": [
            "<schema.org/description>",
            "<schema.org/image>",
            "<schema.org/mainEntityOfPage>",
            "<schema.org/name>",
            "<schema.org/potentialAction>",
            "<schema.org/url>",
            "isa:<schema.org/ServiceChannel>"
        ],
        "count": 13.0
    },
    {
        "pset": [
            "<schema.org/availableLanguage>",
            "<schema.org/description>",
            "<schema.org/name>",
            "<schema.org/servicePhone>",
            "<schema.org/url>",
            "isa:<schema.org/ServiceChannel>"
        ],
        "count": 10.0
    },
    {
        "pset": [
            "<schema.org/description>",
            "<schema.org/image>",
            "<schema.org/name>",
            "<schema.org/providesService>",
            "<schema.org/serviceUrl>",
            "isa:<schema.org/ServiceChannel>"
        ],
        "count": 10.0
    },
    {
        "pset": [
            "<schema.org/availableLanguage>",
            "<schema.org/providesService>",
            "<schema.org/servicePostalAddress>",
            "<schema.org/serviceUrl>",
            "isa:<schema.org/ServiceChannel>"
        ],
        "count": 8.0
    },
    {
        "pset": [
            "<schema.org/servicePostalAddress>",
            "<schema.org/serviceUrl>",
            "isa:<schema.org/ServiceChannel>"
        ],
        "count": 8.0
    },
    {
        "pset": [
            "<schema.org/mainEntityOfPage>",
            "<schema.org/name>",
            "<schema.org/serviceUrl>",
            "isa:<schema.org/ServiceChannel>"
        ],
        "count": 6.0
    },
    {
        "pset": [
            "<schema.org/name>",
            "<schema.org/providesService>",
            "<schema.org/servicePostalAddress>",
            "isa:<schema.org/ServiceChannel>"
        ],
        "count": 6.0
    },
    {
        "pset": [
            "<schema.org/address>",
            "<schema.org/geo>",
            "<schema.org/image>",
            "<schema.org/name>",
            "<schema.org/openingHoursSpecification>",
            "<schema.org/priceRange>",
            "<schema.org/telephone>",
            "<schema.org/url>",
            "isa:<schema.org/ServiceChannel>"
        ],
        "count": 6.0
    },
    {
        "pset": [
            "<schema.org/name>",
            "<schema.org/serviceLocation>",
            "<schema.org/serviceUrl>",
            "isa:<schema.org/ServiceChannel>"
        ],
        "count": 6.0
    },
    {
        "pset": [
            "<schema.org/description>",
            "<schema.org/name>",
            "<schema.org/serviceLocation>",
            "<schema.org/servicePhone>",
            "<schema.org/serviceUrl>",
            "isa:<schema.org/Organization>",
            "isa:<schema.org/ServiceChannel>"
        ],
        "count": 5.0
    },
    {
        "pset": [
            "<schema.org/description>",
            "<schema.org/name>",
            "<schema.org/serviceLocation>",
            "<schema.org/servicePhone>",
            "<schema.org/serviceURL>",
            "isa:<schema.org/ServiceChannel>"
        ],
        "count": 5.0
    },
    {
        "pset": [
            "<schema.org/areaServed>",
            "<schema.org/availableChannel>",
            "<schema.org/description>",
            "<schema.org/image>",
            "<schema.org/name>",
            "<schema.org/provider>",
            "<schema.org/serviceLocation>",
            "<schema.org/serviceOutput>",
            "<schema.org/servicePhone>",
            "<schema.org/serviceType>",
            "<schema.org/serviceURL>",
            "<schema.org/url>",
            "isa:<schema.org/Service>",
            "isa:<schema.org/ServiceChannel>"
        ],
        "count": 5.0
    },
    {
        "pset": [
            "<schema.org/description>",
            "<schema.org/serviceLocation>",
            "<schema.org/servicePhone>",
            "<schema.org/serviceUrl>",
            "isa:<schema.org/ServiceChannel>"
        ],
        "count": 4.0
    },
    {
        "pset": [
            "<schema.org/description>",
            "<schema.org/serviceUrl>",
            "isa:<schema.org/ServiceChannel>"
        ],
        "count": 4.0
    },
    {
        "pset": [
            "<schema.org/ContactPoint>",
            "<schema.org/description>",
            "<schema.org/name>",
            "<schema.org/serviceLocation>",
            "<schema.org/serviceUrl>",
            "isa:<schema.org/ServiceChannel>"
        ],
        "count": 4.0
    },
    {
        "pset": [
            "<schema.org/areaServed>",
            "<schema.org/audience>",
            "<schema.org/availableChannel>",
            "<schema.org/availableLanguage>",
            "<schema.org/contactType>",
            "<schema.org/description>",
            "<schema.org/image>",
            "<schema.org/name>",
            "<schema.org/provider>",
            "<schema.org/serviceLocation>",
            "<schema.org/serviceOutput>",
            "<schema.org/servicePhone>",
            "<schema.org/serviceType>",
            "<schema.org/serviceUrl>",
            "<schema.org/telephone>",
            "<schema.org/url>",
            "isa:<schema.org/ContactPoint>",
            "isa:<schema.org/Service>",
            "isa:<schema.org/ServiceChannel>"
        ],
        "count": 4.0
    },
    {
        "pset": [
            "<schema.org/name>",
            "<schema.org/servicePhone>",
            "isa:<schema.org/ServiceChannel>"
        ],
        "count": 4.0
    },
    {
        "pset": [
            "<schema.org/availableLanguage>",
            "<schema.org/url>",
            "isa:<schema.org/ServiceChannel>"
        ],
        "count": 4.0
    },
    {
        "pset": [
            "<schema.org/availableLanguage>",
            "<schema.org/servicePhone>",
            "<schema.org/serviceURL>",
            "isa:<schema.org/ServiceChannel>"
        ],
        "count": 4.0
    },
    {
        "pset": [
            "<schema.org/name>",
            "<schema.org/serviceLocation>",
            "<schema.org/servicePhone>",
            "<schema.org/serviceUrl>",
            "isa:<schema.org/ServiceChannel>"
        ],
        "count": 4.0
    },
    {
        "pset": [
            "<schema.org/areaServed>",
            "<schema.org/audience>",
            "<schema.org/availableChannel>",
            "<schema.org/description>",
            "<schema.org/image>",
            "<schema.org/name>",
            "<schema.org/provider>",
            "<schema.org/serviceLocation>",
            "<schema.org/servicePhone>",
            "<schema.org/serviceType>",
            "<schema.org/serviceUrl>",
            "<schema.org/url>",
            "isa:<schema.org/Service>",
            "isa:<schema.org/ServiceChannel>",
            "isa:<schema.org/WebPage>"
        ],
        "count": 3.0
    },
    {
        "pset": [
            "<schema.org/description>",
            "<schema.org/name>",
            "<schema.org/serviceLocation>",
            "<schema.org/servicePhone>",
            "isa:<schema.org/ServiceChannel>"
        ],
        "count": 3.0
    },
    {
        "pset": [
            "<schema.org/additionalType>",
            "<schema.org/name>",
            "<schema.org/serviceUrl>",
            "isa:<schema.org/ServiceChannel>"
        ],
        "count": 2.0
    },
    {
        "pset": [
            "<schema.org/areaServed>",
            "<schema.org/availableLanguage>",
            "<schema.org/contactType>",
            "<schema.org/description>",
            "<schema.org/name>",
            "<schema.org/serviceLocation>",
            "<schema.org/servicePhone>",
            "<schema.org/serviceUrl>",
            "<schema.org/telephone>",
            "isa:<schema.org/ContactPoint>",
            "isa:<schema.org/ServiceChannel>"
        ],
        "count": 2.0
    },
    {
        "pset": [
            "<schema.org/name>",
            "<schema.org/providesService>",
            "<schema.org/servicePhone>",
            "<schema.org/serviceUrl>",
            "<schema.org/url>",
            "isa:<schema.org/ServiceChannel>"
        ],
        "count": 2.0
    },
    {
        "pset": [
            "<schema.org/serviceLocation>",
            "<schema.org/servicePhone>",
            "isa:<schema.org/ServiceChannel>"
        ],
        "count": 2.0
    },
    {
        "pset": [
            "<schema.org/name>",
            "<schema.org/processingTime>",
            "<schema.org/servicePhone>",
            "<schema.org/serviceUrl>",
            "isa:<schema.org/ServiceChannel>"
        ],
        "count": 2.0
    },
    {
        "pset": [
            "<schema.org/availableLanguage>",
            "<schema.org/processingTime>",
            "<schema.org/providesService>",
            "<schema.org/serviceLocation>",
            "<schema.org/servicePhone>",
            "<schema.org/servicePostalAddress>",
            "<schema.org/serviceUrl>",
            "isa:<schema.org/ServiceChannel>"
        ],
        "count": 2.0
    },
    {
        "pset": [
            "<schema.org/areaServed>",
            "<schema.org/contactType>",
            "<schema.org/description>",
            "<schema.org/faxNumber>",
            "<schema.org/name>",
            "<schema.org/serviceLocation>",
            "<schema.org/servicePhone>",
            "<schema.org/serviceUrl>",
            "<schema.org/telephone>",
            "isa:<schema.org/City>",
            "isa:<schema.org/ContactPoint>",
            "isa:<schema.org/ServiceChannel>"
        ],
        "count": 2.0
    },
    {
        "pset": [
            "<schema.org/areaServed>",
            "<schema.org/availableChannel>",
            "<schema.org/description>",
            "<schema.org/image>",
            "<schema.org/name>",
            "<schema.org/provider>",
            "<schema.org/serviceLocation>",
            "<schema.org/serviceOutput>",
            "<schema.org/servicePhone>",
            "<schema.org/serviceType>",
            "<schema.org/serviceUrl>",
            "<schema.org/url>",
            "isa:<schema.org/Organization>",
            "isa:<schema.org/Service>",
            "isa:<schema.org/ServiceChannel>"
        ],
        "count": 2.0
    },
    {
        "pset": [
            "<schema.org/availableLanguage>",
            "<schema.org/servicePhone>",
            "isa:<schema.org/ServiceChannel>"
        ],
        "count": 2.0
    },
    {
        "pset": [
            "<schema.org/providesService>",
            "<schema.org/serviceURL>",
            "isa:<schema.org/ServiceChannel>"
        ],
        "count": 2.0
    },
    {
        "pset": [
            "<schema.org/providesService>",
            "<schema.org/serviceLocation>",
            "<schema.org/servicePhone>",
            "<schema.org/servicePostalAddress>",
            "<schema.org/serviceSmsNumber>",
            "<schema.org/serviceUrl>",
            "isa:<schema.org/ServiceChannel>"
        ],
        "count": 1.0
    },
    {
        "pset": [
            "<schema.org/availableLanguage>",
            "<schema.org/servicePostalAddress>",
            "<schema.org/url>",
            "isa:<schema.org/ServiceChannel>"
        ],
        "count": 1.0
    },
    {
        "pset": [
            "<schema.org/areaServed>",
            "<schema.org/availableLanguage>",
            "<schema.org/contactType>",
            "<schema.org/description>",
            "<schema.org/faxNumber>",
            "<schema.org/name>",
            "<schema.org/servicePhone>",
            "<schema.org/serviceUrl>",
            "<schema.org/telephone>",
            "isa:<schema.org/ContactPoint>",
            "isa:<schema.org/ServiceChannel>"
        ],
        "count": 1.0
    },
    {
        "pset": [
            "<schema.org/availableLanguage>",
            "<schema.org/name>",
            "<schema.org/providesService>",
            "<schema.org/servicePhone>",
            "<schema.org/url>",
            "isa:<schema.org/ServiceChannel>"
        ],
        "count": 1.0
    },
    {
        "pset": [
            "<schema.org/ContactPoint>",
            "<schema.org/areaServed>",
            "<schema.org/audience>",
            "<schema.org/availableChannel>",
            "<schema.org/description>",
            "<schema.org/image>",
            "<schema.org/name>",
            "<schema.org/provider>",
            "<schema.org/serviceLocation>",
            "<schema.org/serviceOutput>",
            "<schema.org/serviceType>",
            "<schema.org/serviceUrl>",
            "<schema.org/url>",
            "isa:<schema.org/Service>",
            "isa:<schema.org/ServiceChannel>"
        ],
        "count": 1.0
    },
    {
        "pset": [
            "<schema.org/availableLanguage>",
            "<schema.org/providesService>",
            "<schema.org/serviceLocation>",
            "<schema.org/servicePhone>",
            "<schema.org/servicePostalAddress>",
            "<schema.org/serviceUrl>",
            "isa:<schema.org/ServiceChannel>"
        ],
        "count": 1.0
    },
    {
        "pset": [
            "<schema.org/name>",
            "<schema.org/providesService>",
            "<schema.org/servicePhone>",
            "isa:<schema.org/ServiceChannel>"
        ],
        "count": 1.0
    },
    {
        "pset": [
            "<schema.org/additionalType>",
            "<schema.org/alternateName>",
            "<schema.org/availableLanguage>",
            "<schema.org/description>",
            "<schema.org/image>",
            "<schema.org/mainEntityOfPage>",
            "<schema.org/name>",
            "<schema.org/providesService>",
            "<schema.org/sameAs>",
            "<schema.org/serviceLocation>",
            "<schema.org/servicePhone>",
            "<schema.org/servicePostalAddress>",
            "<schema.org/serviceUrl>",
            "isa:<schema.org/ServiceChannel>"
        ],
        "count": 1.0
    },
    {
        "pset": [
            "<schema.org/areaServed>",
            "<schema.org/availableChannel>",
            "<schema.org/description>",
            "<schema.org/name>",
            "<schema.org/provider>",
            "<schema.org/serviceLocation>",
            "<schema.org/serviceOutput>",
            "<schema.org/servicePhone>",
            "<schema.org/serviceType>",
            "<schema.org/serviceUrl>",
            "<schema.org/url>",
            "isa:<schema.org/Organization>",
            "isa:<schema.org/Service>",
            "isa:<schema.org/ServiceChannel>"
        ],
        "count": 1.0
    },
    {
        "pset": [
            "<schema.org/availableChannel>",
            "<schema.org/description>",
            "<schema.org/name>",
            "<schema.org/provider>",
            "<schema.org/serviceLocation>",
            "<schema.org/serviceOutput>",
            "<schema.org/servicePhone>",
            "<schema.org/serviceType>",
            "<schema.org/serviceUrl>",
            "<schema.org/url>",
            "isa:<schema.org/Service>",
            "isa:<schema.org/ServiceChannel>"
        ],
        "count": 1.0
    },
    {
        "pset": [
            "<schema.org/alternateName>",
            "<schema.org/availableLanguage>",
            "<schema.org/description>",
            "<schema.org/name>",
            "<schema.org/processingTime>",
            "<schema.org/providesService>",
            "<schema.org/serviceLocation>",
            "<schema.org/serviceUrl>",
            "isa:<schema.org/ServiceChannel>"
        ],
        "count": 1.0
    },
    {
        "pset": [
            "<schema.org/description>",
            "<schema.org/image>",
            "<schema.org/name>",
            "<schema.org/providesService>",
            "<schema.org/servicePhone>",
            "<schema.org/serviceUrl>",
            "<schema.org/url>",
            "isa:<schema.org/ServiceChannel>"
        ],
        "count": 1.0
    },
    {
        "pset": [
            "<schema.org/alternateName>",
            "<schema.org/description>",
            "<schema.org/mainEntityOfPage>",
            "<schema.org/name>",
            "<schema.org/servicePhone>",
            "<schema.org/serviceUrl>",
            "isa:<schema.org/ServiceChannel>"
        ],
        "count": 1.0
    },
    {
        "pset": [
            "<schema.org/areaServed>",
            "<schema.org/availableLanguage>",
            "<schema.org/contactType>",
            "<schema.org/description>",
            "<schema.org/name>",
            "<schema.org/servicePhone>",
            "<schema.org/serviceUrl>",
            "<schema.org/telephone>",
            "isa:<schema.org/ContactPoint>",
            "isa:<schema.org/ServiceChannel>"
        ],
        "count": 1.0
    },
    {
        "pset": [
            "<schema.org/description>",
            "<schema.org/name>",
            "<schema.org/serviceLocation>",
            "<schema.org/servicePhone>",
            "<schema.org/url>",
            "isa:<schema.org/ServiceChannel>"
        ],
        "count": 1.0
    },
    {
        "pset": [
            "<schema.org/availableLanguage>",
            "<schema.org/contactType>",
            "<schema.org/description>",
            "<schema.org/email>",
            "<schema.org/name>",
            "<schema.org/serviceLocation>",
            "<schema.org/servicePhone>",
            "<schema.org/serviceUrl>",
            "<schema.org/telephone>",
            "isa:<schema.org/ContactPoint>",
            "isa:<schema.org/ServiceChannel>"
        ],
        "count": 1.0
    },
    {
        "pset": [
            "<schema.org/availableLanguage>",
            "<schema.org/description>",
            "<schema.org/name>",
            "<schema.org/sameAs>",
            "<schema.org/serviceLocation>",
            "isa:<schema.org/ServiceChannel>"
        ],
        "count": 1.0
    },
    {
        "pset": [
            "isa:<schema.org/ServiceChannel>"
        ],
        "count": 1.0
    },
    {
        "pset": [
            "<schema.org/description>",
            "<schema.org/name>",
            "<schema.org/providesService>",
            "<schema.org/sameAs>",
            "<schema.org/servicePhone>",
            "<schema.org/url>",
            "isa:<schema.org/ServiceChannel>"
        ],
        "count": 1.0
    },
    {
        "pset": [
            "<schema.org/availableLanguage>",
            "<schema.org/contactType>",
            "<schema.org/description>",
            "<schema.org/name>",
            "<schema.org/servicePhone>",
            "<schema.org/serviceUrl>",
            "<schema.org/telephone>",
            "isa:<schema.org/ContactPoint>",
            "isa:<schema.org/ServiceChannel>"
        ],
        "count": 1.0
    },
    {
        "pset": [
            "<schema.org/availableLanguage>",
            "<schema.org/contactType>",
            "<schema.org/description>",
            "<schema.org/name>",
            "<schema.org/serviceLocation>",
            "<schema.org/servicePhone>",
            "<schema.org/serviceUrl>",
            "<schema.org/telephone>",
            "isa:<schema.org/ContactPoint>",
            "isa:<schema.org/ServiceChannel>"
        ],
        "count": 1.0
    },
    {
        "pset": [
            "<schema.org/servicePhone>",
            "<schema.org/servicePostalAddress>",
            "<schema.org/serviceUrl>",
            "isa:<schema.org/ServiceChannel>"
        ],
        "count": 1.0
    },
    {
        "pset": [
            "<schema.org/name>",
            "<schema.org/sameAs>",
            "<schema.org/url>",
            "isa:<schema.org/ServiceChannel>"
        ],
        "count": 1.0
    },
    {
        "pset": [
            "<schema.org/description>",
            "<schema.org/height>",
            "<schema.org/name>",
            "<schema.org/serviceLocation>",
            "<schema.org/servicePhone>",
            "<schema.org/serviceUrl>",
            "<schema.org/url>",
            "<schema.org/width>",
            "isa:<schema.org/ImageObject>",
            "isa:<schema.org/ServiceChannel>"
        ],
        "count": 1.0
    },
    {
        "pset": [
            "<schema.org/description>",
            "<schema.org/name>",
            "<schema.org/servicePhone>",
            "<schema.org/servicePostalAddress>",
            "<schema.org/serviceUrl>",
            "isa:<schema.org/ServiceChannel>"
        ],
        "count": 1.0
    },
    {
        "pset": [
            "<schema.org/availableLanguage>",
            "<schema.org/name>",
            "<schema.org/servicePhone>",
            "<schema.org/servicePostalAddress>",
            "<schema.org/serviceURL>",
            "isa:<schema.org/ServiceChannel>"
        ],
        "count": 1.0
    },
    {
        "pset": [
            "<schema.org/additionalType>",
            "<schema.org/alternateName>",
            "<schema.org/availableLanguage>",
            "<schema.org/description>",
            "<schema.org/disambiguatingDescription>",
            "<schema.org/identifier>",
            "<schema.org/mainEntityOfPage>",
            "<schema.org/name>",
            "<schema.org/potentialAction>",
            "<schema.org/providesService>",
            "<schema.org/serviceLocation>",
            "<schema.org/servicePhone>",
            "<schema.org/servicePostalAddress>",
            "<schema.org/serviceUrl>",
            "<schema.org/url>",
            "isa:<schema.org/ServiceChannel>"
        ],
        "count": 1.0
    },
    {
        "pset": [
            "<schema.org/areaServed>",
            "<schema.org/audience>",
            "<schema.org/availableChannel>",
            "<schema.org/description>",
            "<schema.org/image>",
            "<schema.org/name>",
            "<schema.org/provider>",
            "<schema.org/serviceLocation>",
            "<schema.org/serviceOutput>",
            "<schema.org/servicePhone>",
            "<schema.org/serviceType>",
            "<schema.org/serviceUrl>",
            "<schema.org/url>",
            "isa:<schema.org/Organization>",
            "isa:<schema.org/Service>",
            "isa:<schema.org/ServiceChannel>"
        ],
        "count": 1.0
    },
    {
        "pset": [
            "<schema.org/name>",
            "<schema.org/servicePhone>",
            "<schema.org/serviceUrl>",
            "<schema.org/url>",
            "isa:<schema.org/ServiceChannel>"
        ],
        "count": 1.0
    },
    {
        "pset": [
            "<schema.org/description>",
            "<schema.org/mainEntityOfPage>",
            "<schema.org/name>",
            "<schema.org/serviceLocation>",
            "<schema.org/servicePhone>",
            "<schema.org/serviceSmsNumber>",
            "<schema.org/serviceUrl>",
            "<schema.org/url>",
            "isa:<schema.org/ServiceChannel>"
        ],
        "count": 1.0
    },
    {
        "pset": [
            "<schema.org/description>",
            "<schema.org/name>",
            "<schema.org/serviceOutput>",
            "<schema.org/servicePhone>",
            "<schema.org/serviceUrl>",
            "<schema.org/url>",
            "isa:<schema.org/ServiceChannel>"
        ],
        "count": 1.0
    },
    {
        "pset": [
            "<schema.org/description>",
            "<schema.org/name>",
            "<schema.org/serviceLocation>",
            "<schema.org/serviceUrl>",
            "isa:<schema.org/Organization>",
            "isa:<schema.org/ServiceChannel>"
        ],
        "count": 1.0
    },
    {
        "pset": [
            "<schema.org/ServicePhone>",
            "<schema.org/description>",
            "<schema.org/name>",
            "<schema.org/serviceLocation>",
            "<schema.org/serviceUrl>",
            "isa:<schema.org/ServiceChannel>"
        ],
        "count": 1.0
    },
    {
        "pset": [
            "<schema.org/serviceUrl>",
            "<schema.org/url>",
            "isa:<schema.org/ServiceChannel>"
        ],
        "count": 1.0
    },
    {
        "pset": [
            "<schema.org/description>",
            "<schema.org/image>",
            "<schema.org/mainEntityOfPage>",
            "<schema.org/name>",
            "<schema.org/url>",
            "isa:<schema.org/ServiceChannel>"
        ],
        "count": 1.0
    },
    {
        "pset": [
            "<schema.org/description>",
            "<schema.org/servicePhone>",
            "<schema.org/serviceUrl>",
            "isa:<schema.org/ServiceChannel>"
        ],
        "count": 1.0
    },
    {
        "pset": [
            "<schema.org/areaServed>",
            "<schema.org/availableLanguage>",
            "<schema.org/contactType>",
            "<schema.org/description>",
            "<schema.org/faxNumber>",
            "<schema.org/name>",
            "<schema.org/serviceLocation>",
            "<schema.org/servicePhone>",
            "<schema.org/serviceUrl>",
            "<schema.org/telephone>",
            "isa:<schema.org/ContactPoint>",
            "isa:<schema.org/ServiceChannel>"
        ],
        "count": 1.0
    },
    {
        "pset": [
            "<schema.org/description>",
            "<schema.org/name>",
            "<schema.org/servicePhone>",
            "<schema.org/url>",
            "isa:<schema.org/ServiceChannel>"
        ],
        "count": 1.0
    }
]